{
	"info": {
		"_postman_id": "2dc545bf-f17b-43c6-b656-c568bc7796b2",
		"name": "intern-assignment",
		"schema": "https://schema.getpostman.com/json/collection/v2.1.0/collection.json",
		"_exporter_id": "48345608",
		"_collection_link": "https://likhith1201-2852235.postman.co/workspace/Likhith-Pullela's-Workspace~c94a3356-043e-46a4-804a-6c73c2190412/collection/48345608-2dc545bf-f17b-43c6-b656-c568bc7796b2?action=share&source=collection_link&creator=48345608"
	},
	"item": [
		{
			"name": "http://localhost:5000/api/v1/users/register",
			"request": {
				"auth": {
					"type": "noauth"
				},
				"method": "POST",
				"header": [
					{
						"key": "Key",
						"value": "Content-Type",
						"type": "text"
					},
					{
						"key": "Value",
						"value": "application/json",
						"type": "text"
					}
				],
				"body": {
					"mode": "raw",
					"raw": "{\r\n  \"name\": \"Test User\",\r\n  \"email\": \"test@example.com\",\r\n  \"password\": \"password123\"\r\n}",
					"options": {
						"raw": {
							"language": "json"
						}
					}
				},
				"url": {
					"raw": "http://localhost:5000/api/v1/users/register",
					"protocol": "http",
					"host": [
						"localhost"
					],
					"port": "5000",
					"path": [
						"api",
						"users",
						"register"
					]
				}
			},
			"response": []
		},
		{
			"name": "http://localhost:5000/api/v1/users/login",
			"request": {
				"auth": {
					"type": "noauth"
				},
				"method": "POST",
				"header": [
					{
						"key": "Key",
						"value": "Content-Type",
						"type": "text"
					},
					{
						"key": "Value",
						"value": "application/json",
						"type": "text"
					}
				],
				"body": {
					"mode": "raw",
					"raw": "{\r\n  \"email\": \"test@example.com\",\r\n  \"password\": \"password123\"\r\n}",
					"options": {
						"raw": {
							"language": "json"
						}
					}
				},
				"url": {
					"raw": "http://localhost:5000/api/v1/users/login",
					"protocol": "http",
					"host": [
						"localhost"
					],
					"port": "5000",
					"path": [
						"api",
						"users",
						"login"
					]
				}
			},
			"response": []
		},
		{
			"name": "http://localhost:5000/api/v1/users/login",
			"request": {
				"auth": {
					"type": "noauth"
				},
				"method": "POST",
				"header": [
					{
						"key": "Key",
						"value": "Content-Type",
						"type": "text"
					},
					{
						"key": "Value",
						"value": "application/json",
						"type": "text"
					}
				],
				"body": {
					"mode": "raw",
					"raw": "{\r\n  \"email\": \"test@example.com\",\r\n  \"password\": \"password13\"\r\n}",
					"options": {
						"raw": {
							"language": "json"
						}
					}
				},
				"url": {
					"raw": "http://localhost:5000/api/v1users/login",
					"protocol": "http",
					"host": [
						"localhost"
					],
					"port": "5000",
					"path": [
						"api",
						"users",
						"login"
					]
				}
			},
			"response": []
		},
		{
			"name": "http://localhost:5000/api/v1/users/profile",
			"protocolProfileBehavior": {
				"disableBodyPruning": true
			},
			"request": {
				"auth": {
					"type": "noauth"
				},
				"method": "GET",
				"header": [
					{
						"key": "Key",
						"value": "Content-Type",
						"type": "text"
					},
					{
						"key": "Value",
						"value": "application/json",
						"type": "text"
					}
				],
				"body": {
					"mode": "raw",
					"raw": "{\r\n  \"email\": \"test@example.com\",\r\n  \"password\": \"password13\"\r\n}",
					"options": {
						"raw": {
							"language": "json"
						}
					}
				},
				"url": {
					"raw": "http://localhost:5000/api/v1/users/profile",
					"protocol": "http",
					"host": [
						"localhost"
					],
					"port": "5000",
					"path": [
						"api",
						"users",
						"profile"
					]
				}
			},
			"response": []
		},
		{
			"name": "http://localhost:5000/api/v1/users/login",
			"request": {
				"auth": {
					"type": "noauth"
				},
				"method": "POST",
				"header": [
					{
						"key": "Key",
						"value": "Content-Type",
						"type": "text"
					},
					{
						"key": "Value",
						"value": "application/json",
						"type": "text"
					}
				],
				"body": {
					"mode": "raw",
					"raw": "{\r\n  \"email\": \"test@example.com\",\r\n  \"password\": \"password123\"\r\n}",
					"options": {
						"raw": {
							"language": "json"
						}
					}
				},
				"url": {
					"raw": "http://localhost:5000/api/v1/users/login",
					"protocol": "http",
					"host": [
						"localhost"
					],
					"port": "5000",
					"path": [
						"api",
						"users",
						"login"
					]
				}
			},
			"response": []
		},
		{
			"name": "http://localhost:5000/api/v1/users/profile",
			"protocolProfileBehavior": {
				"disableBodyPruning": true
			},
			"request": {
				"auth": {
					"type": "bearer",
					"bearer": [
						{
							"key": "token",
							"value": "http://localhost:5000/api/v1/users/profile",
							"type": "string"
						}
					]
				},
				"method": "GET",
				"header": [
					{
						"key": "Key",
						"value": "Content-Type",
						"type": "text"
					},
					{
						"key": "Value",
						"value": "application/json",
						"type": "text"
					}
				],
				"body": {
					"mode": "raw",
					"raw": "{\r\n  \"email\": \"test@example.com\",\r\n  \"password\": \"password123\"\r\n}",
					"options": {
						"raw": {
							"language": "json"
						}
					}
				},
				"url": {
					"raw": "http://localhost:5000/api/v1/users/profile",
					"protocol": "http",
					"host": [
						"localhost"
					],
					"port": "5000",
					"path": [
						"api",
						"users",
						"profile"
					]
				}
			},
			"response": []
		},
		{
			"name": "http://localhost:5000/api/v1/users/profile",
			"protocolProfileBehavior": {
				"disableBodyPruning": true
			},
			"request": {
				"auth": {
					"type": "bearer",
					"bearer": [
						{
							"key": "token",
							"value": "eyJhbGciOiJIUzI1NiIsInR5cCI6IkpXVCJ9.eyJpZCI6IjY5MGRhM2I4ZDM1ZWVkNzJiMTkzMmMyZCIsImlhdCI6MTc2MjUwMTkxMCwiZXhwIjoxNzY1MDkzOTEwfQ.gUVE0VwVmoqhvXmb_q-m_8KyXidKSRN77biBHw6RsOs",
							"type": "string"
						}
					]
				},
				"method": "GET",
				"header": [
					{
						"key": "Key",
						"value": "Content-Type",
						"type": "text"
					},
					{
						"key": "Value",
						"value": "application/json",
						"type": "text"
					}
				],
				"body": {
					"mode": "raw",
					"raw": "{\r\n  \"email\": \"test@example.com\",\r\n  \"password\": \"password123\"\r\n}",
					"options": {
						"raw": {
							"language": "json"
						}
					}
				},
				"url": {
					"raw": "http://localhost:5000/api/v1/users/profile",
					"protocol": "http",
					"host": [
						"localhost"
					],
					"port": "5000",
					"path": [
						"api",
						"users",
						"profile"
					]
				}
			},
			"response": []
		},
		{
			"name": "http://localhost:5000/api/v1/users/login",
			"request": {
				"auth": {
					"type": "bearer",
					"bearer": [
						{
							"key": "token",
							"value": "eyJhbGciOiJIUzI1NiIsInR5cCI6IkpXVCJ9.eyJpZCI6IjY5MGRhM2I4ZDM1ZWVkNzJiMTkzMmMyZCIsImlhdCI6MTc2MjUwMTkxMCwiZXhwIjoxNzY1MDkzOTEwfQ.gUVE0VwVmoqhvXmb_q-m_8KyXidKSRN77biBHw6RsOs",
							"type": "string"
						}
					]
				},
				"method": "POST",
				"header": [
					{
						"key": "Key",
						"value": "Content-Type",
						"type": "text"
					},
					{
						"key": "Value",
						"value": "application/json",
						"type": "text"
					}
				],
				"body": {
					"mode": "raw",
					"raw": "{\r\n  \"email\": \"test@example.com\",\r\n  \"password\": \"password123\"\r\n}",
					"options": {
						"raw": {
							"language": "json"
						}
					}
				},
				"url": {
					"raw": "http://localhost:5000/api/v1/users/login",
					"protocol": "http",
					"host": [
						"localhost"
					],
					"port": "5000",
					"path": [
						"api",
						"users",
						"login"
					]
				}
			},
			"response": []
		},
		{
			"name": "http://localhost:5000/api/v1/tasks",
			"request": {
				"auth": {
					"type": "bearer",
					"bearer": [
						{
							"key": "token",
							"value": "eyJhbGciOiJIUzI1NiIsInR5cCI6IkpXVCJ9.eyJpZCI6IjY5MGRhM2I4ZDM1ZWVkNzJiMTkzMmMyZCIsImlhdCI6MTc2MjUwMjI1MSwiZXhwIjoxNzY1MDk0MjUxfQ.WbKJHuBntCYkLxYqH25mFft7r3PG_vDScdGA7dSx9qI",
							"type": "string"
						}
					]
				},
				"method": "POST",
				"header": [
					{
						"key": "Key",
						"value": "Content-Type",
						"type": "text"
					},
					{
						"key": "Value",
						"value": "application/json",
						"type": "text"
					}
				],
				"body": {
					"mode": "raw",
					"raw": "{\r\n  \"title\": \"My First Task\",\r\n  \"description\": \"Complete the backend API.\"\r\n}",
					"options": {
						"raw": {
							"language": "json"
						}
					}
				},
				"url": {
					"raw": "http://localhost:5000/api/v1/tasks",
					"protocol": "http",
					"host": [
						"localhost"
					],
					"port": "5000",
					"path": [
						"api",
						"tasks"
					]
				}
			},
			"response": []
		},
		{
			"name": "http://localhost:5000/api/v1/tasks/mytasks",
			"protocolProfileBehavior": {
				"disableBodyPruning": true
			},
			"request": {
				"auth": {
					"type": "bearer",
					"bearer": [
						{
							"key": "token",
							"value": "eyJhbGciOiJIUzI1NiIsInR5cCI6IkpXVCJ9.eyJpZCI6IjY5MGRhM2I4ZDM1ZWVkNzJiMTkzMmMyZCIsImlhdCI6MTc2MjUwMjI1MSwiZXhwIjoxNzY1MDk0MjUxfQ.WbKJHuBntCYkLxYqH25mFft7r3PG_vDScdGA7dSx9qI",
							"type": "string"
						}
					]
				},
				"method": "GET",
				"header": [
					{
						"key": "Key",
						"value": "Content-Type",
						"type": "text"
					},
					{
						"key": "Value",
						"value": "application/json",
						"type": "text"
					}
				],
				"body": {
					"mode": "raw",
					"raw": "{\r\n  \"title\": \"My First Task\",\r\n  \"description\": \"Complete the backend API.\"\r\n}",
					"options": {
						"raw": {
							"language": "json"
						}
					}
				},
				"url": {
					"raw": "http://localhost:5000/api/v1/tasks/mytasks",
					"protocol": "http",
					"host": [
						"localhost"
					],
					"port": "5000",
					"path": [
						"api",
						"tasks",
						"mytasks"
					]
				}
			},
			"response": []
		},
		{
			"name": "http://localhost:5000/api/v1/tasks/all",
			"protocolProfileBehavior": {
				"disableBodyPruning": true
			},
			"request": {
				"auth": {
					"type": "bearer",
					"bearer": [
						{
							"key": "token",
							"value": "eyJhbGciOiJIUzI1NiIsInR5cCI6IkpXVCJ9.eyJpZCI6IjY5MGRhM2I4ZDM1ZWVkNzJiMTkzMmMyZCIsImlhdCI6MTc2MjUwMjI1MSwiZXhwIjoxNzY1MDk0MjUxfQ.WbKJHuBntCYkLxYqH25mFft7r3PG_vDScdGA7dSx9qI",
							"type": "string"
						}
					]
				},
				"method": "GET",
				"header": [
					{
						"key": "Key",
						"value": "Content-Type",
						"type": "text"
					},
					{
						"key": "Value",
						"value": "application/json",
						"type": "text"
					}
				],
				"body": {
					"mode": "raw",
					"raw": "{\r\n  \"title\": \"My First Task\",\r\n  \"description\": \"Complete the backend API.\"\r\n}",
					"options": {
						"raw": {
							"language": "json"
						}
					}
				},
				"url": {
					"raw": "http://localhost:5000/api/v1/tasks/all",
					"protocol": "http",
					"host": [
						"localhost"
					],
					"port": "5000",
					"path": [
						"api",
						"tasks",
						"all"
					]
				}
			},
			"response": []
		},
		{
			"name": "http://localhost:5000/api/v1/users/login",
			"protocolProfileBehavior": {
				"disableBodyPruning": true
			},
			"request": {
				"auth": {
					"type": "bearer",
					"bearer": [
						{
							"key": "token",
							"value": "eyJhbGciOiJIUzI1NiIsInR5cCI6IkpXVCJ9.eyJpZCI6IjY5MGRhM2I4ZDM1ZWVkNzJiMTkzMmMyZCIsImlhdCI6MTc2MjUwMjI1MSwiZXhwIjoxNzY1MDk0MjUxfQ.WbKJHuBntCYkLxYqH25mFft7r3PG_vDScdGA7dSx9qI",
							"type": "string"
						}
					]
				},
				"method": "GET",
				"header": [
					{
						"key": "Key",
						"value": "Content-Type",
						"type": "text"
					},
					{
						"key": "Value",
						"value": "application/json",
						"type": "text"
					}
				],
				"body": {
					"mode": "raw",
					"raw": "{\r\n  \"email\": \"test@example.com\",\r\n  \"password\": \"password123\"\r\n}",
					"options": {
						"raw": {
							"language": "json"
						}
					}
				},
				"url": {
					"raw": "http://localhost:5000/api/v1/users/login",
					"protocol": "http",
					"host": [
						"localhost"
					],
					"port": "5000",
					"path": [
						"api",
						"users",
						"login"
					]
				}
			},
			"response": []
		},
		{
			"name": "http://localhost:5000/api/v1/users/login",
			"request": {
				"auth": {
					"type": "bearer",
					"bearer": [
						{
							"key": "token",
							"value": "eyJhbGciOiJIUzI1NiIsInR5cCI6IkpXVCJ9.eyJpZCI6IjY5MGRhM2I4ZDM1ZWVkNzJiMTkzMmMyZCIsImlhdCI6MTc2MjUwMjI1MSwiZXhwIjoxNzY1MDk0MjUxfQ.WbKJHuBntCYkLxYqH25mFft7r3PG_vDScdGA7dSx9qI",
							"type": "string"
						}
					]
				},
				"method": "POST",
				"header": [
					{
						"key": "Key",
						"value": "Content-Type",
						"type": "text"
					},
					{
						"key": "Value",
						"value": "application/json",
						"type": "text"
					}
				],
				"body": {
					"mode": "raw",
					"raw": "{\r\n  \"email\": \"test@example.com\",\r\n  \"password\": \"password123\"\r\n}",
					"options": {
						"raw": {
							"language": "json"
						}
					}
				},
				"url": {
					"raw": "http://localhost:5000/api/v1/users/login",
					"protocol": "http",
					"host": [
						"localhost"
					],
					"port": "5000",
					"path": [
						"api",
						"users",
						"login"
					]
				}
			},
			"response": []
		},
		{
			"name": "http://localhost:5000/api/v1/tasks/all",
			"protocolProfileBehavior": {
				"disableBodyPruning": true
			},
			"request": {
				"auth": {
					"type": "bearer",
					"bearer": [
						{
							"key": "token",
							"value": "eyJhbGciOiJIUzI1NiIsInR5cCI6IkpXVCJ9.eyJpZCI6IjY5MGRhM2I4ZDM1ZWVkNzJiMTkzMmMyZCIsImlhdCI6MTc2MjUwMzI1NywiZXhwIjoxNzY1MDk1MjU3fQ.3lI2WramzSna8TgVMgCT0hmCrsxWWNU1v1J97ckbrkU",
							"type": "string"
						}
					]
				},
				"method": "GET",
				"header": [
					{
						"key": "Key",
						"value": "Content-Type",
						"type": "text"
					},
					{
						"key": "Value",
						"value": "application/json",
						"type": "text"
					}
				],
				"body": {
					"mode": "raw",
					"raw": "{\r\n  \"email\": \"test@example.com\",\r\n  \"password\": \"password123\"\r\n}",
					"options": {
						"raw": {
							"language": "json"
						}
					}
				},
				"url": {
					"raw": "http://localhost:5000/api/v1/tasks/all",
					"protocol": "http",
					"host": [
						"localhost"
					],
					"port": "5000",
					"path": [
						"api",
						"tasks",
						"all"
					]
				}
			},
			"response": []
		}
	]
}